pyautotk/__init__.py
pyautotk/core/__init__.py
pyautotk/core/browser_controller.py
pyautotk/core/config_loader.py
pyautotk/core/exceptions.py
pyautotk/core/logger_utils.py
pyautotk/elements/__init__.py
pyautotk/elements/widget.py
pyautotk/elements/helpers/__init__.py
pyautotk/elements/helpers/session_helpers.py
pyautotk/examples/browser_examples.py
pyautotk-0.4.0.dist-info/LICENSE
pyautotk-0.4.0.dist-info/METADATA
pyautotk-0.4.0.dist-info/WHEEL
pyautotk-0.4.0.dist-info/top_level.txt
pyautotk-0.4.0.dist-info/RECORD
