Metadata-Version: 2.1
Name: pyautotk
Version: 0.4.0
Summary: Page Object framework helper
Author-email: "Gabriel Ramos R. Oliveira" <bielrammos@gmail.com>
Project-URL: Homepage, https://github.com/brailog/PyAutoTk
Project-URL: Issues, https://github.com/brailog/PyAutoTk
Project-URL: Documentation, https://pyautotk.readthedocs.io/en/latest/
Classifier: Programming Language :: Python :: 3
Classifier: License :: OSI Approved :: MIT License
Classifier: Operating System :: OS Independent
Requires-Python: >=3.8
License-File: LICENSE
Requires-Dist: selenium >=4.25.0
Requires-Dist: urllib3 >=1.26.16
Requires-Dist: attrs >=24.2.0
Requires-Dist: idna >=3.10
Requires-Dist: pillow >=10.4.0
Requires-Dist: PySocks >=1.7.1
Requires-Dist: sniffio >=1.3.1
Requires-Dist: sortedcontainers >=2.4.0
Requires-Dist: trio >=0.26.2
Requires-Dist: trio-websocket >=0.11.1
Requires-Dist: typing-extensions >=4.12.2
Requires-Dist: websocket-client >=1.8.0
Requires-Dist: wsproto >=1.2.0
Provides-Extra: dev
Requires-Dist: black >=22.10.0 ; extra == 'dev'
Requires-Dist: pre-commit >=4.0.0 ; extra == 'dev'
